MANIFEST.in
setup.cfg
setup.py
test.py
core/__init__.py
core/download.py
core/options.py
core/prefab.py
munidatapipeline/__init__.py
munidatapipeline/munidatapipeline.py
munidatapipeline.egg-info/PKG-INFO
munidatapipeline.egg-info/SOURCES.txt
munidatapipeline.egg-info/dependency_links.txt
munidatapipeline.egg-info/top_level.txt