Metadata-Version: 1.0
Name: munidatapipeline
Version: 0.2.2
Summary: An ETL tool for working with municipal open data (especially GiS data) on resource constrained systems.
Home-page: https://github.com/mdp-dev/munidatapipeline
Author: Charles Landau, Andrew Gobbi
Author-email: munidatapipelinedevelopment@gmail.com
License: UNKNOWN
Keywords: munidatapipeline,ETL,multiprocessing
Platform: UNKNOWN
